py3cw/__init__.py
py3cw/config.py
py3cw/request.py
py3cw/test_request.py
py3cw/utils.py
py3cw-0.1.1.dist-info/LICENSE
py3cw-0.1.1.dist-info/METADATA
py3cw-0.1.1.dist-info/WHEEL
py3cw-0.1.1.dist-info/top_level.txt
py3cw-0.1.1.dist-info/RECORD
